docs/original/library/experiment.py
examples/src/armory/examples/__init__.py
examples/src/armory/examples/display.py
examples/src/armory/examples/image_classification/cifar10_jatic_toolbox.py
examples/src/armory/examples/image_classification/imagenet1k_resnet34_pgd.py
examples/src/armory/examples/image_classification/kaludi_food_category_pgd.py
examples/src/armory/examples/image_classification/mnist_vit_pgd.py
examples/src/armory/examples/image_classification/pokemon_pgd.py
examples/src/armory/examples/image_classification/eurosat_precomputed_pgd/create_adversarial_eurosat.py
examples/src/armory/examples/image_classification/eurosat_precomputed_pgd/create_finetuned_model.py
examples/src/armory/examples/image_classification/eurosat_precomputed_pgd/evaluation.py
examples/src/armory/examples/image_classification/eurosat_precomputed_pgd/run_against_pregenerated.py
examples/src/armory/examples/image_classification/eurosat_precomputed_pgd/run_with_attack.py
examples/src/armory/examples/image_classification/food101/food101_pgd.py
examples/src/armory/examples/image_classification/food101/food101_train.py
examples/src/armory/examples/object_detection/coco_fasterrcnn_resnet50_robustdpatch.py
examples/src/armory/examples/object_detection/coco_yolos_robustdpatch.py
examples/src/armory/examples/object_detection/license_plates_yolov5_robustdpatch.py
examples/src/armory/examples/object_detection/coco_precomputed_patch/create_adversarial_dataset.py
examples/src/armory/examples/object_detection/coco_precomputed_patch/evaluation.py
examples/src/armory/examples/object_detection/coco_precomputed_patch/run_against_pregenerated.py
examples/src/armory/examples/object_detection/coco_precomputed_patch/run_with_attack.py
examples/src/armory/examples/object_detection/xview/train_xview_model.py
examples/src/armory/examples/object_detection/xview/xview_fasterrcnn_robustdpatch.py
examples/src/armory/examples/utils/__init__.py
examples/src/armory/examples/utils/args.py
armory_suite-0.0.0.dist-info/METADATA
armory_suite-0.0.0.dist-info/WHEEL
armory_suite-0.0.0.dist-info/licenses/LICENSE
armory_suite-0.0.0.dist-info/RECORD
