Metadata-Version: 2.1
Name: armory-suite
Version: 0.0.0
License-File: LICENSE
Requires-Python: >=3.8
Requires-Dist: black[jupyter]
Requires-Dist: flake8
Requires-Dist: hatch
Requires-Dist: ipykernel
Requires-Dist: ipywidgets
Requires-Dist: isort
Requires-Dist: mkdocs
Requires-Dist: mkdocs-exclude
Requires-Dist: mkdocs-material
Requires-Dist: mkdocstrings-python
Requires-Dist: pre-commit
Requires-Dist: pytest
Requires-Dist: setuptools-scm
Requires-Dist: taskipy
Requires-Dist: wheel
